gists/__init__.py
python_gists_import-1.0.2.dist-info/LICENSE
python_gists_import-1.0.2.dist-info/METADATA
python_gists_import-1.0.2.dist-info/WHEEL
python_gists_import-1.0.2.dist-info/RECORD
