Metadata-Version: 2.1
Name: python-gists-import
Version: 1.0.2
Summary: 🐍📦 this Python package provides a very convenient way to import GitHub gists in a pythonic way using `import` statements. 
Home-page: https://github.com/LaurenzBeck/gists.git
License: MIT
Keywords: Python,GitHub,gists,import,deployment,🐍,📦
Author: Farthofer Laurenz
Author-email: laurenz@hey.com
Requires-Python: >=3.11,<4.0
Classifier: License :: OSI Approved :: MIT License
Classifier: Programming Language :: Python :: 3
Classifier: Programming Language :: Python :: 3.11
Classifier: Programming Language :: Python :: 3.12
Requires-Dist: gist-import (>=1.0.4,<2.0.0)
Requires-Dist: loguru (>=0.7.2,<0.8.0)
Project-URL: Repository, https://github.com/LaurenzBeck/gists.git
